{"Id":"7244469a-9544-4b2e-8fbb-7d65501780f9","LogDateUtc":"2017-10-18T20:33:14.2726884Z","IpAddress":"","Culture":"en-US","Url":"","ShortUrl":"","Thread":"","LogLevel":"Information","Logger":"Microsoft.AspNetCore.Authentication.Cookies.CookieAuthenticationHandler","Message":"AuthenticationScheme: Identity.Application was successfully authenticated.","StateJson":"[{\"Key\":\"AuthenticationScheme\",\"Value\":\"Identity.Application\"},{\"Key\":\"{OriginalFormat}\",\"Value\":\"AuthenticationScheme: {AuthenticationScheme} was successfully authenticated.\"}]","EventId":8}